[
  {
    "id": 1,
    "question": "자신의 선택이 때로는 외로운 길로 이어진다고 느끼나요?",
    "answer": {
      "text": "예",
      "increment": [
        1,
        9
      ]
    }
  },
  {
    "id": 2,
    "question": "시험이나 평가에서 항상 좋은 성적을 받아야 마음이 편한가요?",
    "answer": {
      "text": "예",
      "increment": [
        0,
        9
      ]
    }
  },
  {
    "id": 3,
    "question": "때때로 자신이 배경에 가려진 것처럼 느껴지나요?",
    "answer": {
      "text": "예",
      "increment": [
        2,
        4
      ]
    }
  },
  {
    "id": 4,
    "question": "단순한 힘보다는 머리를 쓰는 것이 더 강력한 무기라고 생각하나요?",
    "answer": {
      "text": "예",
      "increment": [
        11,
        10
      ]
    }
  },
  {
    "id": 5,
    "question": "남들이 모르는 내면의 고통이 있더라도 겉으로는 감추는 편인가요?",
    "answer": {
      "text": "예",
      "increment": [
        3,
        9
      ]
    }
  },
  {
    "id": 6,
    "question": "과거의 실패가 현재의 행동을 결정하는 데 큰 영향을 주나요?",
    "answer": {
      "text": "예",
      "increment": [
        1,
        11
      ]
    }
  },
  {
    "id": 7,
    "question": "꾸준함이 결국 성공을 만든다고 믿나요?",
    "answer": {
      "text": "예",
      "increment": [
        6,
        7
      ]
    }
  },
  {
    "id": 8,
    "question": "경쟁보다는 모두가 성장할 수 있는 환경이 더 중요하다고 느끼나요?",
    "answer": {
      "text": "예",
      "increment": [
        8,
        4
      ]
    }
  },
  {
    "id": 9,
    "question": "남들이 알아주지 않아도 맡은 일을 묵묵히 해내는 편인가요?",
    "answer": {
      "text": "예",
      "increment": [
        2,
        10
      ]
    }
  },
  {
    "id": 10,
    "question": "남들과 다른 시각으로 세상을 바라보는 것이 즐겁나요?",
    "answer": {
      "text": "예",
      "increment": [
        3,
        5
      ]
    }
  },
  {
    "id": 11,
    "question": "책임감이 강한 편인가요?",
    "answer": {
      "text": "예",
      "increment": [
        1,
        5
      ]
    }
  },
  {
    "id": 12,
    "question": "작은 변화가 큰 차이를 만든다고 생각하나요?",
    "answer": {
      "text": "예",
      "increment": [
        10,
        4
      ]
    }
  },
  {
    "id": 13,
    "question": "모든 것을 계획하고 대비하는 것이 중요하다고 생각하나요?",
    "answer": {
      "text": "예",
      "increment": [
        6,
        9
      ]
    }
  },
  {
    "id": 14,
    "question": "실수를 하면 오래 신경 쓰는 편인가요?",
    "answer": {
      "text": "예",
      "increment": [
        9,
        2
      ]
    }
  },
  {
    "id": 15,
    "question": "주변 사람들의 감정을 잘 읽는 편인가요?",
    "answer": {
      "text": "예",
      "increment": [
        7,
        8
      ]
    }
  }
]